cstvis/__init__.py
cstvis/changer.py
cstvis/collector.py
cstvis/dto.py
cstvis/py.typed
cstvis/transformers/__init__.py
cstvis/transformers/super_transformer.py
cstvis/utils/__init__.py
cstvis/utils/function_id.py
cstvis/visitors/__init__.py
cstvis/visitors/bloodhound.py
cstvis/visitors/comments_aggregator.py
cstvis-0.0.2.dist-info/LICENSE
cstvis-0.0.2.dist-info/METADATA
cstvis-0.0.2.dist-info/WHEEL
cstvis-0.0.2.dist-info/top_level.txt
cstvis-0.0.2.dist-info/RECORD
